{
    "annotations": {
        "list": [
            {
                "builtIn": 1,
                "datasource": {
                    "type": "grafana",
                    "uid": "-- Grafana --"
                },
                "enable": true,
                "hide": true,
                "iconColor": "rgba(0, 211, 255, 1)",
                "name": "Annotations & Alerts",
                "target": {
                    "limit": 100,
                    "matchAny": false,
                    "tags": [],
                    "type": "dashboard"
                },
                "type": "dashboard"
            }
        ]
    },
    "editable": true,
    "fiscalYearStartMonth": 0,
    "graphTooltip": 0,
    "id": 2,
    "links": [],
    "liveNow": false,
    "panels": [
        {
            "datasource": {},
            "fieldConfig": {
                "defaults": {
                    "color": {
                        "mode": "palette-classic"
                    },
                    "custom": {
                        "axisCenteredZero": false,
                        "axisColorMode": "text",
                        "axisLabel": "",
                        "axisPlacement": "auto",
                        "barAlignment": 0,
                        "drawStyle": "line",
                        "fillOpacity": 50,
                        "gradientMode": "opacity",
                        "hideFrom": {
                            "legend": false,
                            "tooltip": false,
                            "viz": false
                        },
                        "lineInterpolation": "smooth",
                        "lineWidth": 2,
                        "pointSize": 5,
                        "scaleDistribution": {
                            "type": "linear"
                        },
                        "showPoints": "auto",
                        "spanNulls": false,
                        "stacking": {
                            "group": "A",
                            "mode": "none"
                        },
                        "thresholdsStyle": {
                            "mode": "off"
                        }
                    },
                    "mappings": [],
                    "thresholds": {
                        "mode": "absolute",
                        "steps": [
                            {
                                "color": "green",
                                "value": null
                            },
                            {
                                "color": "red",
                                "value": 80
                            }
                        ]
                    },
                    "unit": "short"
                },
                "overrides": []
            },
            "gridPos": {
                "h": 6,
                "w": 12,
                "x": 0,
                "y": 0
            },
            "id": 2,
            "options": {
                "legend": {
                    "calcs": [],
                    "displayMode": "list",
                    "placement": "bottom",
                    "showLegend": true
                },
                "tooltip": {
                    "mode": "single",
                    "sort": "none"
                }
            },
            "targets": [
                {
                    "datasource": {
                        "type": "prometheus",
                        "uid": "55KqKRp4z"
                    },
                    "editorMode": "code",
                    "expr": "nginx_connections_active",
                    "legendFormat": "{{ instance }}",
                    "range": true,
                    "refId": "A"
                }
            ],
            "title": "Active Connections",
            "type": "timeseries"
        },
        {
            "datasource": {},
            "fieldConfig": {
                "defaults": {
                    "color": {
                        "mode": "palette-classic"
                    },
                    "custom": {
                        "axisCenteredZero": false,
                        "axisColorMode": "text",
                        "axisLabel": "",
                        "axisPlacement": "auto",
                        "barAlignment": 0,
                        "drawStyle": "line",
                        "fillOpacity": 50,
                        "gradientMode": "opacity",
                        "hideFrom": {
                            "legend": false,
                            "tooltip": false,
                            "viz": false
                        },
                        "lineInterpolation": "smooth",
                        "lineWidth": 2,
                        "pointSize": 5,
                        "scaleDistribution": {
                            "type": "linear"
                        },
                        "showPoints": "auto",
                        "spanNulls": false,
                        "stacking": {
                            "group": "A",
                            "mode": "none"
                        },
                        "thresholdsStyle": {
                            "mode": "off"
                        }
                    },
                    "decimals": 2,
                    "mappings": [],
                    "thresholds": {
                        "mode": "absolute",
                        "steps": [
                            {
                                "color": "green",
                                "value": null
                            },
                            {
                                "color": "red",
                                "value": 80
                            }
                        ]
                    },
                    "unit": "reqps"
                },
                "overrides": []
            },
            "gridPos": {
                "h": 6,
                "w": 12,
                "x": 12,
                "y": 0
            },
            "id": 9,
            "options": {
                "legend": {
                    "calcs": [],
                    "displayMode": "list",
                    "placement": "bottom",
                    "showLegend": true,
                    "sortBy": "Last *",
                    "sortDesc": true
                },
                "tooltip": {
                    "mode": "single",
                    "sort": "none"
                }
            },
            "targets": [
                {
                    "datasource": {
                        "type": "prometheus",
                        "uid": "55KqKRp4z"
                    },
                    "editorMode": "code",
                    "expr": "rate(nginx_http_requests_total[1m])",
                    "legendFormat": "{{ instance }}",
                    "range": true,
                    "refId": "A"
                }
            ],
            "title": "Total Requests (req/s)",
            "type": "timeseries"
        },
        {
            "datasource": {},
            "fieldConfig": {
                "defaults": {
                    "color": {
                        "mode": "palette-classic"
                    },
                    "custom": {
                        "axisCenteredZero": false,
                        "axisColorMode": "text",
                        "axisLabel": "",
                        "axisPlacement": "auto",
                        "barAlignment": 0,
                        "drawStyle": "line",
                        "fillOpacity": 50,
                        "gradientMode": "opacity",
                        "hideFrom": {
                            "legend": false,
                            "tooltip": false,
                            "viz": false
                        },
                        "lineInterpolation": "smooth",
                        "lineWidth": 2,
                        "pointSize": 5,
                        "scaleDistribution": {
                            "type": "linear"
                        },
                        "showPoints": "auto",
                        "spanNulls": false,
                        "stacking": {
                            "group": "A",
                            "mode": "none"
                        },
                        "thresholdsStyle": {
                            "mode": "off"
                        }
                    },
                    "mappings": [],
                    "thresholds": {
                        "mode": "absolute",
                        "steps": [
                            {
                                "color": "green",
                                "value": null
                            },
                            {
                                "color": "red",
                                "value": 80
                            }
                        ]
                    },
                    "unit": "short"
                },
                "overrides": []
            },
            "gridPos": {
                "h": 6,
                "w": 12,
                "x": 0,
                "y": 6
            },
            "id": 6,
            "options": {
                "legend": {
                    "calcs": [],
                    "displayMode": "list",
                    "placement": "bottom",
                    "showLegend": true
                },
                "tooltip": {
                    "mode": "single",
                    "sort": "none"
                }
            },
            "targets": [
                {
                    "datasource": {
                        "type": "prometheus",
                        "uid": "55KqKRp4z"
                    },
                    "editorMode": "code",
                    "expr": "nginx_connections_reading",
                    "legendFormat": "{{ instance }}",
                    "range": true,
                    "refId": "A"
                }
            ],
            "title": "Reading Connections",
            "type": "timeseries"
        },
        {
            "datasource": {},
            "fieldConfig": {
                "defaults": {
                    "color": {
                        "mode": "palette-classic"
                    },
                    "custom": {
                        "axisCenteredZero": false,
                        "axisColorMode": "text",
                        "axisLabel": "",
                        "axisPlacement": "auto",
                        "barAlignment": 0,
                        "drawStyle": "line",
                        "fillOpacity": 50,
                        "gradientMode": "opacity",
                        "hideFrom": {
                            "legend": false,
                            "tooltip": false,
                            "viz": false
                        },
                        "lineInterpolation": "smooth",
                        "lineWidth": 2,
                        "pointSize": 5,
                        "scaleDistribution": {
                            "type": "linear"
                        },
                        "showPoints": "auto",
                        "spanNulls": false,
                        "stacking": {
                            "group": "A",
                            "mode": "none"
                        },
                        "thresholdsStyle": {
                            "mode": "off"
                        }
                    },
                    "decimals": 2,
                    "mappings": [],
                    "thresholds": {
                        "mode": "absolute",
                        "steps": [
                            {
                                "color": "green",
                                "value": null
                            },
                            {
                                "color": "red",
                                "value": 80
                            }
                        ]
                    },
                    "unit": "reqps"
                },
                "overrides": []
            },
            "gridPos": {
                "h": 6,
                "w": 12,
                "x": 12,
                "y": 6
            },
            "id": 4,
            "options": {
                "legend": {
                    "calcs": [],
                    "displayMode": "list",
                    "placement": "bottom",
                    "showLegend": true,
                    "sortBy": "Last *",
                    "sortDesc": true
                },
                "tooltip": {
                    "mode": "single",
                    "sort": "none"
                }
            },
            "targets": [
                {
                    "datasource": {
                        "type": "prometheus",
                        "uid": "55KqKRp4z"
                    },
                    "editorMode": "code",
                    "expr": "rate(nginx_connections_accepted[1m])",
                    "legendFormat": "{{ instance }}",
                    "range": true,
                    "refId": "A"
                }
            ],
            "title": "Accepted Connections (req/s)",
            "type": "timeseries"
        },
        {
            "datasource": {},
            "fieldConfig": {
                "defaults": {
                    "color": {
                        "mode": "palette-classic"
                    },
                    "custom": {
                        "axisCenteredZero": false,
                        "axisColorMode": "text",
                        "axisLabel": "",
                        "axisPlacement": "auto",
                        "barAlignment": 0,
                        "drawStyle": "line",
                        "fillOpacity": 50,
                        "gradientMode": "opacity",
                        "hideFrom": {
                            "legend": false,
                            "tooltip": false,
                            "viz": false
                        },
                        "lineInterpolation": "smooth",
                        "lineWidth": 2,
                        "pointSize": 5,
                        "scaleDistribution": {
                            "type": "linear"
                        },
                        "showPoints": "auto",
                        "spanNulls": false,
                        "stacking": {
                            "group": "A",
                            "mode": "none"
                        },
                        "thresholdsStyle": {
                            "mode": "off"
                        }
                    },
                    "mappings": [],
                    "thresholds": {
                        "mode": "absolute",
                        "steps": [
                            {
                                "color": "green",
                                "value": null
                            },
                            {
                                "color": "red",
                                "value": 80
                            }
                        ]
                    },
                    "unit": "short"
                },
                "overrides": []
            },
            "gridPos": {
                "h": 6,
                "w": 12,
                "x": 0,
                "y": 12
            },
            "id": 7,
            "options": {
                "legend": {
                    "calcs": [],
                    "displayMode": "list",
                    "placement": "bottom",
                    "showLegend": true
                },
                "tooltip": {
                    "mode": "single",
                    "sort": "none"
                }
            },
            "targets": [
                {
                    "datasource": {
                        "type": "prometheus",
                        "uid": "55KqKRp4z"
                    },
                    "editorMode": "code",
                    "expr": "nginx_connections_waiting",
                    "legendFormat": "{{ instance }}",
                    "range": true,
                    "refId": "A"
                }
            ],
            "title": "Waiting Connections",
            "type": "timeseries"
        },
        {
            "datasource": {},
            "fieldConfig": {
                "defaults": {
                    "color": {
                        "mode": "palette-classic"
                    },
                    "custom": {
                        "axisCenteredZero": false,
                        "axisColorMode": "text",
                        "axisLabel": "",
                        "axisPlacement": "auto",
                        "barAlignment": 0,
                        "drawStyle": "line",
                        "fillOpacity": 50,
                        "gradientMode": "opacity",
                        "hideFrom": {
                            "legend": false,
                            "tooltip": false,
                            "viz": false
                        },
                        "lineInterpolation": "smooth",
                        "lineWidth": 2,
                        "pointSize": 5,
                        "scaleDistribution": {
                            "type": "linear"
                        },
                        "showPoints": "auto",
                        "spanNulls": false,
                        "stacking": {
                            "group": "A",
                            "mode": "none"
                        },
                        "thresholdsStyle": {
                            "mode": "off"
                        }
                    },
                    "decimals": 2,
                    "mappings": [],
                    "thresholds": {
                        "mode": "absolute",
                        "steps": [
                            {
                                "color": "green",
                                "value": null
                            },
                            {
                                "color": "red",
                                "value": 80
                            }
                        ]
                    },
                    "unit": "reqps"
                },
                "overrides": []
            },
            "gridPos": {
                "h": 6,
                "w": 12,
                "x": 12,
                "y": 12
            },
            "id": 5,
            "options": {
                "legend": {
                    "calcs": [],
                    "displayMode": "list",
                    "placement": "bottom",
                    "showLegend": true,
                    "sortBy": "Last *",
                    "sortDesc": true
                },
                "tooltip": {
                    "mode": "single",
                    "sort": "none"
                }
            },
            "targets": [
                {
                    "datasource": {
                        "type": "prometheus",
                        "uid": "55KqKRp4z"
                    },
                    "editorMode": "code",
                    "expr": "rate(nginx_connections_handled[1m])",
                    "legendFormat": "{{ instance }}",
                    "range": true,
                    "refId": "A"
                }
            ],
            "title": "Handled Connections (req/s)",
            "type": "timeseries"
        },
        {
            "datasource": {},
            "fieldConfig": {
                "defaults": {
                    "color": {
                        "mode": "palette-classic"
                    },
                    "custom": {
                        "axisCenteredZero": false,
                        "axisColorMode": "text",
                        "axisLabel": "",
                        "axisPlacement": "auto",
                        "barAlignment": 0,
                        "drawStyle": "line",
                        "fillOpacity": 50,
                        "gradientMode": "opacity",
                        "hideFrom": {
                            "legend": false,
                            "tooltip": false,
                            "viz": false
                        },
                        "lineInterpolation": "smooth",
                        "lineWidth": 2,
                        "pointSize": 5,
                        "scaleDistribution": {
                            "type": "linear"
                        },
                        "showPoints": "auto",
                        "spanNulls": false,
                        "stacking": {
                            "group": "A",
                            "mode": "none"
                        },
                        "thresholdsStyle": {
                            "mode": "off"
                        }
                    },
                    "mappings": [],
                    "thresholds": {
                        "mode": "absolute",
                        "steps": [
                            {
                                "color": "green",
                                "value": null
                            },
                            {
                                "color": "red",
                                "value": 80
                            }
                        ]
                    },
                    "unit": "short"
                },
                "overrides": []
            },
            "gridPos": {
                "h": 6,
                "w": 24,
                "x": 0,
                "y": 18
            },
            "id": 8,
            "options": {
                "legend": {
                    "calcs": [],
                    "displayMode": "list",
                    "placement": "bottom",
                    "showLegend": true
                },
                "tooltip": {
                    "mode": "single",
                    "sort": "none"
                }
            },
            "targets": [
                {
                    "datasource": {
                        "type": "prometheus",
                        "uid": "55KqKRp4z"
                    },
                    "editorMode": "code",
                    "expr": "nginx_connections_writing",
                    "legendFormat": "{{ instance }}",
                    "range": true,
                    "refId": "A"
                }
            ],
            "title": "Writing Connections",
            "type": "timeseries"
        }
    ],
    "refresh": "5s",
    "schemaVersion": 37,
    "style": "dark",
    "tags": [],
    "templating": {
        "list": []
    },
    "time": {
        "from": "now-30m",
        "to": "now"
    },
    "timepicker": {},
    "timezone": "",
    "title": "Nginx",
    "uid": "vblgcgt4k",
    "version": 2,
    "weekStart": ""
}